democicd/__init__.py
democicd/cli.py
democicd/main.py
democicd-0.1.5.dist-info/LICENSE
democicd-0.1.5.dist-info/METADATA
democicd-0.1.5.dist-info/WHEEL
democicd-0.1.5.dist-info/entry_points.txt
democicd-0.1.5.dist-info/top_level.txt
democicd-0.1.5.dist-info/RECORD
