Metadata-Version: 2.2
Name: democicd
Version: 0.1.5
Summary: A demonstration CI/CD pipeline project.
Author-email: lorenzo del medico <lorenzodelmedico@gmail.com>
License: MIT License
Project-URL: Homepage, https://github.com/lorenzodelmedico/democicd
Project-URL: Repository, https://github.com/lorenzodelmedico/democicd
Keywords: Fun,Utile,Best application,Gamechanging,Amazing,Mew,Best functionnality,Lorenzodelmedico
Requires-Python: >=3.8
License-File: LICENSE
Requires-Dist: astroid==3.3.8
Requires-Dist: black==25.1.0
Requires-Dist: click==8.1.8
Requires-Dist: dill==0.3.9
Requires-Dist: exceptiongroup==1.2.2
Requires-Dist: iniconfig==2.0.0
Requires-Dist: isort==6.0.0
Requires-Dist: mccabe==0.7.0
Requires-Dist: mypy-extensions==1.0.0
Requires-Dist: packaging==24.2
Requires-Dist: pathspec==0.12.1
Requires-Dist: platformdirs==4.3.6
Requires-Dist: pluggy==1.5.0
Requires-Dist: pylint==3.3.4
Requires-Dist: pytest==8.3.4
Requires-Dist: tomli==2.2.1
Requires-Dist: tomlkit==0.13.2
Requires-Dist: typing_extensions==4.12.2
